<?xml version="1.0" encoding="UTF-8"?>
<objects serializationModel="Studio.02.02.00">
	<object class="AudioFile" id="{d870bb90-dcd1-4646-84d6-07e4c7ca1b0f}">
		<property name="assetPath">
			<value>Music/Light Stage 1 Ambient.mp3</value>
		</property>
		<property name="isStreaming">
			<value>true</value>
		</property>
		<property name="frequencyInKHz">
			<value>48</value>
		</property>
		<property name="channelCount">
			<value>2</value>
		</property>
		<property name="length">
			<value>271.05599999999998</value>
		</property>
		<relationship name="masterAssetFolder">
			<destination>{2c94f61a-fee6-44a7-9991-bd48818b8f2c}</destination>
		</relationship>
	</object>
</objects>
